aiidalab_launch/__init__.py
aiidalab_launch/__main__.py
aiidalab_launch/application_state.py
aiidalab_launch/config.py
aiidalab_launch/core.py
aiidalab_launch/instance.py
aiidalab_launch/profile.py
aiidalab_launch/util.py
aiidalab_launch/version.py
aiidalab_launch-2024.1020.dist-info/LICENSE
aiidalab_launch-2024.1020.dist-info/METADATA
aiidalab_launch-2024.1020.dist-info/WHEEL
aiidalab_launch-2024.1020.dist-info/entry_points.txt
aiidalab_launch-2024.1020.dist-info/top_level.txt
aiidalab_launch-2024.1020.dist-info/RECORD
