Metadata-Version: 2.1
Name: aiidalab_launch
Version: 2024.1020
Summary: Tool to launch AiiDAlab on a local workstation.
Home-page: https://github.com/aiidalab/aiidalab-launch
Author: Carl Simon Adorf and the AiiDAlab team
Author-email: aiidalab@materialscloud.org
License: MIT
Classifier: Development Status :: 4 - Beta
Classifier: Framework :: AiiDA
Classifier: License :: OSI Approved :: MIT License
Classifier: Programming Language :: Python :: 3
Classifier: Programming Language :: Python :: 3 :: Only
Classifier: Programming Language :: Python :: Implementation :: CPython
Requires-Python: >=3.8
License-File: LICENSE
Requires-Dist: click ==8.1
Requires-Dist: click-spinner ==0.1.10
Requires-Dist: docker ==7.0.0
Requires-Dist: packaging ==21.3
Requires-Dist: requests ==2.26.0
Requires-Dist: requests-cache ==0.9.1
Requires-Dist: tabulate ==0.9.0
Requires-Dist: toml ==0.10.2
Provides-Extra: dev
Requires-Dist: bumpver ==2023.1129 ; extra == 'dev'
Requires-Dist: dunamai ==1.19.0 ; extra == 'dev'
Requires-Dist: pre-commit ==3.5.0 ; extra == 'dev'
Provides-Extra: tests
Requires-Dist: pytest ~=7.4.3 ; extra == 'tests'
Requires-Dist: pytest-asyncio ~=0.21.1 ; extra == 'tests'
Requires-Dist: pytest-cov ~=4.1.0 ; extra == 'tests'
Requires-Dist: responses ~=0.23.1 ; extra == 'tests'
